Workbook

Sheet Dashboard
B2: Bluewave Electronics — Sales Performance Dashboard 2025
B3: Sample data for demonstration. Choose a region in the yellow cell to filter every number and chart.
B5: Region | C5: All
B8: Total Revenue | C8: Total Profit | D8: Profit Margin | E8: Orders | F8: Avg Order Value | H8: Target Achieved
B9: =SUMPRODUCT((((Dashboard!$C$5="All")+('Sales Data'!$D$2:$D$571=Dashboard!$C$5))>0)*'Sales Data'!$J$2:$J$571) -> 631480 | C9: =SUMPRODUCT((((Dashboard!$C$5="All")+('Sales Data'!$D$2:$D$571=Dashboard!$C$5))>0)*'Sales Data'!$M$2:$M$571) -> 199733 | D9: =IFERROR(C9/B9,0) -> 0.31629347 | E9: =SUMPRODUCT(--(((Dashboard!$C$5="All")+('Sales Data'!$D$2:$D$571=Dashboard!$C$5))>0)) -> 570 | F9: =IFERROR(B9/E9,0) -> 1107.8596 | H9: =IFERROR(B9/IF($C$5="All",SUM(Targets!$F$2:$F$13),SUMPRODUCT((Targets!$B$1:$E$1=$C$5&" Target ($)")*Targets!$B$2:$E$13)),0) -> 0.95751327
B12: Month | C12: Revenue ($) | D12: Profit ($) | E12: Target ($) | F12: Achieved % | H12: Region | I12: Revenue ($) | J12: Profit ($) | L12: Top 5 Products | M12: Revenue ($)
B13: Jan | C13: =SUMPRODUCT(('Sales Data'!$C$2:$C$571=1)*(((Dashboard!$C$5="All")+('Sales Data'!$D$2:$D$571=Dashboard!$C$5))>0)*'Sales Data'!$J$2:$J$571) -> 41530 | D13: =SUMPRODUCT(('Sales Data'!$C$2:$C$571=1)*(((Dashboard!$C$5="All")+('Sales Data'!$D$2:$D$571=Dashboard!$C$5))>0)*'Sales Data'!$M$2:$M$571) -> 12310 | E13: =IF($C$5="All",Targets!$F$2,INDEX(Targets!$B$2:$E$2,MATCH($C$5&" Target ($)",Targets!$B$1:$E$1,0))) -> 42000 | F13: =IFERROR(C13/E13,0) -> 0.98880952 | H13: North | I13: =SUMIFS('Sales Data'!$J$2:$J$571,'Sales Data'!$D$2:$D$571,H13) -> 123980 | J13: =SUMIFS('Sales Data'!$M$2:$M$571,'Sales Data'!$D$2:$D$571,H13) -> 37300 | L13: =INDEX(Calc!$A$3:$A$14,MATCH(LARGE(Calc!$C$3:$C$14,1),Calc!$C$3:$C$14,0)) -> Laptop Pro 14 | M13: =INDEX(Calc!$B$3:$B$14,MATCH(LARGE(Calc!$C$3:$C$14,1),Calc!$C$3:$C$14,0)) -> 100700
B14: Feb | C14: =SUMPRODUCT(('Sales Data'!$C$2:$C$571=2)*(((Dashboard!$C$5="All")+('Sales Data'!$D$2:$D$571=Dashboard!$C$5))>0)*'Sales Data'!$J$2:$J$571) -> 30435 | D14: =SUMPRODUCT(('Sales Data'!$C$2:$C$571=2)*(((Dashboard!$C$5="All")+('Sales Data'!$D$2:$D$571=Dashboard!$C$5))>0)*'Sales Data'!$M$2:$M$571) -> 9361 | E14: =IF($C$5="All",Targets!$F$3,INDEX(Targets!$B$3:$E$3,MATCH($C$5&" Target ($)",Targets!$B$1:$E$1,0))) -> 40000 | F14: =IFERROR(C14/E14,0) -> 0.760875 | H14: South | I14: =SUMIFS('Sales Data'!$J$2:$J$571,'Sales Data'!$D$2:$D$571,H14) -> 154550 | J14: =SUMIFS('Sales Data'!$M$2:$M$571,'Sales Data'!$D$2:$D$571,H14) -> 49204 | L14: =INDEX(Calc!$A$3:$A$14,MATCH(LARGE(Calc!$C$3:$C$14,2),Calc!$C$3:$C$14,0)) -> Laptop Air 13 | M14: =INDEX(Calc!$B$3:$B$14,MATCH(LARGE(Calc!$C$3:$C$14,2),Calc!$C$3:$C$14,0)) -> 94380
B15: Mar | C15: =SUMPRODUCT(('Sales Data'!$C$2:$C$571=3)*(((Dashboard!$C$5="All")+('Sales Data'!$D$2:$D$571=Dashboard!$C$5))>0)*'Sales Data'!$J$2:$J$571) -> 40060 | D15: =SUMPRODUCT(('Sales Data'!$C$2:$C$571=3)*(((Dashboard!$C$5="All")+('Sales Data'!$D$2:$D$571=Dashboard!$C$5))>0)*'Sales Data'!$M$2:$M$571) -> 12942 | E15: =IF($C$5="All",Targets!$F$4,INDEX(Targets!$B$4:$E$4,MATCH($C$5&" Target ($)",Targets!$B$1:$E$1,0))) -> 47500 | F15: =IFERROR(C15/E15,0) -> 0.84336842 | H15: East | I15: =SUMIFS('Sales Data'!$J$2:$J$571,'Sales Data'!$D$2:$D$571,H15) -> 167040 | J15: =SUMIFS('Sales Data'!$M$2:$M$571,'Sales Data'!$D$2:$D$571,H15) -> 54736 | L15: =INDEX(Calc!$A$3:$A$14,MATCH(LARGE(Calc!$C$3:$C$14,3),Calc!$C$3:$C$14,0)) -> Smart Watch | M15: =INDEX(Calc!$B$3:$B$14,MATCH(LARGE(Calc!$C$3:$C$14,3),Calc!$C$3:$C$14,0)) -> 77520
B16: Apr | C16: =SUMPRODUCT(('Sales Data'!$C$2:$C$571=4)*(((Dashboard!$C$5="All")+('Sales Data'!$D$2:$D$571=Dashboard!$C$5))>0)*'Sales Data'!$J$2:$J$571) -> 44775 | D16: =SUMPRODUCT(('Sales Data'!$C$2:$C$571=4)*(((Dashboard!$C$5="All")+('Sales Data'!$D$2:$D$571=Dashboard!$C$5))>0)*'Sales Data'!$M$2:$M$571) -> 13908 | E16: =IF($C$5="All",Targets!$F$5,INDEX(Targets!$B$5:$E$5,MATCH($C$5&" Target ($)",Targets!$B$1:$E$1,0))) -> 50000 | F16: =IFERROR(C16/E16,0) -> 0.8955 | H16: West | I16: =SUMIFS('Sales Data'!$J$2:$J$571,'Sales Data'!$D$2:$D$571,H16) -> 185910 | J16: =SUMIFS('Sales Data'!$M$2:$M$571,'Sales Data'!$D$2:$D$571,H16) -> 58493 | L16: =INDEX(Calc!$A$3:$A$14,MATCH(LARGE(Calc!$C$3:$C$14,4),Calc!$C$3:$C$14,0)) -> Gaming Laptop X | M16: =INDEX(Calc!$B$3:$B$14,MATCH(LARGE(Calc!$C$3:$C$14,4),Calc!$C$3:$C$14,0)) -> 71550
B17: May | C17: =SUMPRODUCT(('Sales Data'!$C$2:$C$571=5)*(((Dashboard!$C$5="All")+('Sales Data'!$D$2:$D$571=Dashboard!$C$5))>0)*'Sales Data'!$J$2:$J$571) -> 47200 | D17: =SUMPRODUCT(('Sales Data'!$C$2:$C$571=5)*(((Dashboard!$C$5="All")+('Sales Data'!$D$2:$D$571=Dashboard!$C$5))>0)*'Sales Data'!$M$2:$M$571) -> 15126 | E17: =IF($C$5="All",Targets!$F$6,INDEX(Targets!$B$6:$E$6,MATCH($C$5&" Target ($)",Targets!$B$1:$E$1,0))) -> 52500 | F17: =IFERROR(C17/E17,0) -> 0.89904762 | L17: =INDEX(Calc!$A$3:$A$14,MATCH(LARGE(Calc!$C$3:$C$14,5),Calc!$C$3:$C$14,0)) -> Phone S23 | M17: =INDEX(Calc!$B$3:$B$14,MATCH(LARGE(Calc!$C$3:$C$14,5),Calc!$C$3:$C$14,0)) -> 64640
B18: Jun | C18: =SUMPRODUCT(('Sales Data'!$C$2:$C$571=6)*(((Dashboard!$C$5="All")+('Sales Data'!$D$2:$D$571=Dashboard!$C$5))>0)*'Sales Data'!$J$2:$J$571) -> 48385 | D18: =SUMPRODUCT(('Sales Data'!$C$2:$C$571=6)*(((Dashboard!$C$5="All")+('Sales Data'!$D$2:$D$571=Dashboard!$C$5))>0)*'Sales Data'!$M$2:$M$571) -> 14821 | E18: =IF($C$5="All",Targets!$F$7,INDEX(Targets!$B$7:$E$7,MATCH($C$5&" Target ($)",Targets!$B$1:$E$1,0))) -> 52500 | F18: =IFERROR(C18/E18,0) -> 0.92161905 | H18: Category | I18: Revenue ($) | J18: Share %
B19: Jul | C19: =SUMPRODUCT(('Sales Data'!$C$2:$C$571=7)*(((Dashboard!$C$5="All")+('Sales Data'!$D$2:$D$571=Dashboard!$C$5))>0)*'Sales Data'!$J$2:$J$571) -> 55555 | D19: =SUMPRODUCT(('Sales Data'!$C$2:$C$571=7)*(((Dashboard!$C$5="All")+('Sales Data'!$D$2:$D$571=Dashboard!$C$5))>0)*'Sales Data'!$M$2:$M$571) -> 16740 | E19: =IF($C$5="All",Targets!$F$8,INDEX(Targets!$B$8:$E$8,MATCH($C$5&" Target ($)",Targets!$B$1:$E$1,0))) -> 50000 | F19: =IFERROR(C19/E19,0) -> 1.1111 | H19: Laptops | I19: =SUMPRODUCT(('Sales Data'!$G$2:$G$571=H19)*(((Dashboard!$C$5="All")+('Sales Data'!$D$2:$D$571=Dashboard!$C$5))>0)*'Sales Data'!$J$2:$J$571) -> 266630 | J19: =IFERROR(I19/SUM($I$19:$I$23),0) -> 0.42223032
B20: Aug | C20: =SUMPRODUCT(('Sales Data'!$C$2:$C$571=8)*(((Dashboard!$C$5="All")+('Sales Data'!$D$2:$D$571=Dashboard!$C$5))>0)*'Sales Data'!$J$2:$J$571) -> 61010 | D20: =SUMPRODUCT(('Sales Data'!$C$2:$C$571=8)*(((Dashboard!$C$5="All")+('Sales Data'!$D$2:$D$571=Dashboard!$C$5))>0)*'Sales Data'!$M$2:$M$571) -> 19445 | E20: =IF($C$5="All",Targets!$F$9,INDEX(Targets!$B$9:$E$9,MATCH($C$5&" Target ($)",Targets!$B$1:$E$1,0))) -> 55500 | F20: =IFERROR(C20/E20,0) -> 1.0992793 | H20: Phones | I20: =SUMPRODUCT(('Sales Data'!$G$2:$G$571=H20)*(((Dashboard!$C$5="All")+('Sales Data'!$D$2:$D$571=Dashboard!$C$5))>0)*'Sales Data'!$J$2:$J$571) -> 106400 | J20: =IFERROR(I20/SUM($I$19:$I$23),0) -> 0.16849306
B21: Sep | C21: =SUMPRODUCT(('Sales Data'!$C$2:$C$571=9)*(((Dashboard!$C$5="All")+('Sales Data'!$D$2:$D$571=Dashboard!$C$5))>0)*'Sales Data'!$J$2:$J$571) -> 61760 | D21: =SUMPRODUCT(('Sales Data'!$C$2:$C$571=9)*(((Dashboard!$C$5="All")+('Sales Data'!$D$2:$D$571=Dashboard!$C$5))>0)*'Sales Data'!$M$2:$M$571) -> 19663 | E21: =IF($C$5="All",Targets!$F$10,INDEX(Targets!$B$10:$E$10,MATCH($C$5&" Target ($)",Targets!$B$1:$E$1,0))) -> 57500 | F21: =IFERROR(C21/E21,0) -> 1.074087 | H21: Tablets | I21: =SUMPRODUCT(('Sales Data'!$G$2:$G$571=H21)*(((Dashboard!$C$5="All")+('Sales Data'!$D$2:$D$571=Dashboard!$C$5))>0)*'Sales Data'!$J$2:$J$571) -> 53720 | J21: =IFERROR(I21/SUM($I$19:$I$23),0) -> 0.085069994
B22: Oct | C22: =SUMPRODUCT(('Sales Data'!$C$2:$C$571=10)*(((Dashboard!$C$5="All")+('Sales Data'!$D$2:$D$571=Dashboard!$C$5))>0)*'Sales Data'!$J$2:$J$571) -> 55420 | D22: =SUMPRODUCT(('Sales Data'!$C$2:$C$571=10)*(((Dashboard!$C$5="All")+('Sales Data'!$D$2:$D$571=Dashboard!$C$5))>0)*'Sales Data'!$M$2:$M$571) -> 17573 | E22: =IF($C$5="All",Targets!$F$11,INDEX(Targets!$B$11:$E$11,MATCH($C$5&" Target ($)",Targets!$B$1:$E$1,0))) -> 60500 | F22: =IFERROR(C22/E22,0) -> 0.91603306 | H22: Monitors | I22: =SUMPRODUCT(('Sales Data'!$G$2:$G$571=H22)*(((Dashboard!$C$5="All")+('Sales Data'!$D$2:$D$571=Dashboard!$C$5))>0)*'Sales Data'!$J$2:$J$571) -> 40630 | J22: =IFERROR(I22/SUM($I$19:$I$23),0) -> 0.064340913
B23: Nov | C23: =SUMPRODUCT(('Sales Data'!$C$2:$C$571=11)*(((Dashboard!$C$5="All")+('Sales Data'!$D$2:$D$571=Dashboard!$C$5))>0)*'Sales Data'!$J$2:$J$571) -> 80890 | D23: =SUMPRODUCT(('Sales Data'!$C$2:$C$571=11)*(((Dashboard!$C$5="All")+('Sales Data'!$D$2:$D$571=Dashboard!$C$5))>0)*'Sales Data'!$M$2:$M$571) -> 25173 | E23: =IF($C$5="All",Targets!$F$12,INDEX(Targets!$B$12:$E$12,MATCH($C$5&" Target ($)",Targets!$B$1:$E$1,0))) -> 71500 | F23: =IFERROR(C23/E23,0) -> 1.1313287 | H23: Accessories | I23: =SUMPRODUCT(('Sales Data'!$G$2:$G$571=H23)*(((Dashboard!$C$5="All")+('Sales Data'!$D$2:$D$571=Dashboard!$C$5))>0)*'Sales Data'!$J$2:$J$571) -> 164100 | J23: =IFERROR(I23/SUM($I$19:$I$23),0) -> 0.25986571
B24: Dec | C24: =SUMPRODUCT(('Sales Data'!$C$2:$C$571=12)*(((Dashboard!$C$5="All")+('Sales Data'!$D$2:$D$571=Dashboard!$C$5))>0)*'Sales Data'!$J$2:$J$571) -> 64460 | D24: =SUMPRODUCT(('Sales Data'!$C$2:$C$571=12)*(((Dashboard!$C$5="All")+('Sales Data'!$D$2:$D$571=Dashboard!$C$5))>0)*'Sales Data'!$M$2:$M$571) -> 22671 | E24: =IF($C$5="All",Targets!$F$13,INDEX(Targets!$B$13:$E$13,MATCH($C$5&" Target ($)",Targets!$B$1:$E$1,0))) -> 80000 | F24: =IFERROR(C24/E24,0) -> 0.80575
B25: Total | C25: =SUM(C13:C24) -> 631480 | D25: =SUM(D13:D24) -> 199733 | E25: =SUM(E13:E24) -> 659500 | F25: =IFERROR(C25/E25,0) -> 0.95751327

Sheet Read Me
A1: Bluewave Electronics — Sales Performance Dashboard
A2: A demo workbook showing Excel dashboard, formula and automation skills. All company names and data are fictional.
A4: How to use
A5: 1. Open the Dashboard sheet and pick a region in the yellow cell (C5). Every KPI, table and chart updates.
A6: 2. Add new orders at the bottom of 'Sales Data' (Order ID, date, region, salesperson, product, units). Price, cost, revenue and profit fill in by formula; copy the formulas down.
A7: 3. Change prices or costs in 'Products', or targets in 'Targets' (blue cells are inputs).
A9: Skills shown
A10: • INDEX/MATCH lookups from a product master table
A11: • SUMIFS and SUMPRODUCT with a region filter controlled by a drop-down (data validation)
A12: • KPI tiles, target vs actual, achievement % with conditional formatting and data bars
A13: • Top 5 products ranking with LARGE + INDEX/MATCH (tie-safe helper column)
A14: • Line and bar charts linked to live formulas
... A22: Data → Get Data → From Other Sources → Blank Query → Advanced Editor → paste CleanSalesData.m → set the file path → Close & Load.

Sheet Sales Data
A1: Order ID | B1: Order Date | C1: Month | D1: Region | E1: Salesperson | F1: Product | G1: Category | H1: Units | I1: Unit Price ($) | J1: Revenue ($) | K1: Unit Cost ($) | L1: Cost ($) | M1: Profit ($)
A2: SO-10003 | B2: 45659 | C2: =MONTH(B2) -> 1 | D2: North | E2: Ayesha Khan | F2: Laptop Air 13 | G2: =IFERROR(INDEX(Products!$B$2:$B$13,MATCH(F2,Products!$A$2:$A$13,0)),"Unknown") -> Laptops | H2: 2 | I2: =IFERROR(INDEX(Products!$C$2:$C$13,MATCH(F2,Products!$A$2:$A$13,0)),0) -> 780 | J2: =H2*I2 -> 1560 | K2: =IFERROR(INDEX(Products!$D$2:$D$13,MATCH(F2,Products!$A$2:$A$13,0)),0) -> 590 | L2: =H2*K2 -> 1180 | M2: =J2-L2 -> 380
A3: SO-10012 | B3: 45660 | C3: =MONTH(B3) -> 1 | D3: South | E3: Usman Tariq | F3: USB-C Hub | G3: =IFERROR(INDEX(Products!$B$2:$B$13,MATCH(F3,Products!$A$2:$A$13,0)),"Unknown") -> Accessories | H3: 12 | I3: =IFERROR(INDEX(Products!$C$2:$C$13,MATCH(F3,Products!$A$2:$A$13,0)),0) -> 45 | J3: =H3*I3 -> 540 | K3: =IFERROR(INDEX(Products!$D$2:$D$13,MATCH(F3,Products!$A$2:$A$13,0)),0) -> 18 | L3: =H3*K3 -> 216 | M3: =J3-L3 -> 324
A4: SO-10018 | B4: 45660 | C4: =MONTH(B4) -> 1 | D4: South | E4: Sara Malik | F4: 27in Monitor | G4: =IFERROR(INDEX(Products!$B$2:$B$13,MATCH(F4,Products!$A$2:$A$13,0)),"Unknown") -> Monitors | H4: 3 | I4: =IFERROR(INDEX(Products!$C$2:$C$13,MATCH(F4,Products!$A$2:$A$13,0)),0) -> 310 | J4: =H4*I4 -> 930 | K4: =IFERROR(INDEX(Products!$D$2:$D$13,MATCH(F4,Products!$A$2:$A$13,0)),0) -> 225 | L4: =H4*K4 -> 675 | M4: =J4-L4 -> 255
A5: SO-10022 | B5: 45660 | C5: =MONTH(B5) -> 1 | D5: North | E5: Ayesha Khan | F5: USB-C Hub | G5: =IFERROR(INDEX(Products!$B$2:$B$13,MATCH(F5,Products!$A$2:$A$13,0)),"Unknown") -> Accessories | H5: 3 | I5: =IFERROR(INDEX(Products!$C$2:$C$13,MATCH(F5,Products!$A$2:$A$13,0)),0) -> 45 | J5: =H5*I5 -> 135 | K5: =IFERROR(INDEX(Products!$D$2:$D$13,MATCH(F5,Products!$A$2:$A$13,0)),0) -> 18 | L5: =H5*K5 -> 54 | M5: =J5-L5 -> 81
A6: SO-10031 | B6: 45660 | C6: =MONTH(B6) -> 1 | D6: West | E6: Zara Sheikh | F6: USB-C Hub | G6: =IFERROR(INDEX(Products!$B$2:$B$13,MATCH(F6,Products!$A$2:$A$13,0)),"Unknown") -> Accessories | H6: 3 | I6: =IFERROR(INDEX(Products!$C$2:$C$13,MATCH(F6,Products!$A$2:$A$13,0)),0) -> 45 | J6: =H6*I6 -> 135 | K6: =IFERROR(INDEX(Products!$D$2:$D$13,MATCH(F6,Products!$A$2:$A$13,0)),0) -> 18 | L6: =H6*K6 -> 54 | M6: =J6-L6 -> 81
A7: SO-10002 | B7: 45665 | C7: =MONTH(B7) -> 1 | D7: South | E7: Usman Tariq | F7: Smart Watch | G7: =IFERROR(INDEX(Products!$B$2:$B$13,MATCH(F7,Products!$A$2:$A$13,0)),"Unknown") -> Accessories | H7: 3 | I7: =IFERROR(INDEX(Products!$C$2:$C$13,MATCH(F7,Products!$A$2:$A$13,0)),0) -> 190 | J7: =H7*I7 -> 570 | K7: =IFERROR(INDEX(Products!$D$2:$D$13,MATCH(F7,Products!$A$2:$A$13,0)),0) -> 115 | L7: =H7*K7 -> 345 | M7: =J7-L7 -> 225
A8: SO-10035 | B8: 45665 | C8: =MONTH(B8) -> 1 | D8: South | E8: Sara Malik | F8: Laptop Pro 14 | G8: =IFERROR(INDEX(Products!$B$2:$B$13,MATCH(F8,Products!$A$2:$A$13,0)),"Unknown") -> Laptops | H8: 1 | I8: =IFERROR(INDEX(Products!$C$2:$C$13,MATCH(F8,Products!$A$2:$A$13,0)),0) -> 950 | J8: =H8*I8 -> 950 | K8: =IFERROR(INDEX(Products!$D$2:$D$13,MATCH(F8,Products!$A$2:$A$13,0)),0) -> 720 | L8: =H8*K8 -> 720 | M8: =J8-L8 -> 230
A9: SO-10020 | B9: 45666 | C9: =MONTH(B9) -> 1 | D9: South | E9: Usman Tariq | F9: Phone S23 | G9: =IFERROR(INDEX(Products!$B$2:$B$13,MATCH(F9,Products!$A$2:$A$13,0)),"Unknown") -> Phones | H9: 2 | I9: =IFERROR(INDEX(Products!$C$2:$C$13,MATCH(F9,Products!$A$2:$A$13,0)),0) -> 640 | J9: =H9*I9 -> 1280 | K9: =IFERROR(INDEX(Products!$D$2:$D$13,MATCH(F9,Products!$A$2:$A$13,0)),0) -> 470 | L9: =H9*K9 -> 940 | M9: =J9-L9 -> 340
A10: SO-10026 | B10: 45667 | C10: =MONTH(B10) -> 1 | D10: West | E10: Ali Hassan | F10: Laptop Air 13 | G10: =IFERROR(INDEX(Products!$B$2:$B$13,MATCH(F10,Products!$A$2:$A$13,0)),"Unknown") -> Laptops | H10: 1 | I10: =IFERROR(INDEX(Products!$C$2:$C$13,MATCH(F10,Products!$A$2:$A$13,0)),0) -> 780 | J10: =H10*I10 -> 780 | K10: =IFERROR(INDEX(Products!$D$2:$D$13,MATCH(F10,Products!$A$2:$A$13,0)),0) -> 590 | L10: =H10*K10 -> 590 | M10: =J10-L10 -> 190
A11: SO-10008 | B11: 45669 | C11: =MONTH(B11) -> 1 | D11: East | E11: Omar Farooq | F11: Wireless Earbuds | G11: =IFERROR(INDEX(Products!$B$2:$B$13,MATCH(F11,Products!$A$2:$A$13,0)),"Unknown") -> Accessories | H11: 3 | I11: =IFERROR(INDEX(Products!$C$2:$C$13,MATCH(F11,Products!$A$2:$A$13,0)),0) -> 85 | J11: =H11*I11 -> 255 | K11: =IFERROR(INDEX(Products!$D$2:$D$13,MATCH(F11,Products!$A$2:$A$13,0)),0) -> 38 | L11: =H11*K11 -> 114 | M11: =J11-L11 -> 141
A12: SO-10034 | B12: 45670 | C12: =MONTH(B12) -> 1 | D12: East | E12: Hina Raza | F12: Tablet 11 | G12: =IFERROR(INDEX(Products!$B$2:$B$13,MATCH(F12,Products!$A$2:$A$13,0)),"Unknown") -> Tablets | H12: 5 | I12: =IFERROR(INDEX(Products!$C$2:$C$13,MATCH(F12,Products!$A$2:$A$13,0)),0) -> 420 | J12: =H12*I12 -> 2100 | K12: =IFERROR(INDEX(Products!$D$2:$D$13,MATCH(F12,Products!$A$2:$A$13,0)),0) -> 300 | L12: =H12*K12 -> 1500 | M12: =J12-L12 -> 600
A13: SO-10005 | B13: 45672 | C13: =MONTH(B13) -> 1 | D13: East | E13: Hina Raza | F13: USB-C Hub | G13: =IFERROR(INDEX(Products!$B$2:$B$13,MATCH(F13,Products!$A$2:$A$13,0)),"Unknown") -> Accessories | H13: 3 | I13: =IFERROR(INDEX(Products!$C$2:$C$13,MATCH(F13,Products!$A$2:$A$13,0)),0) -> 45 | J13: =H13*I13 -> 135 | K13: =IFERROR(INDEX(Products!$D$2:$D$13,MATCH(F13,Products!$A$2:$A$13,0)),0) -> 18 | L13: =H13*K13 -> 54 | M13: =J13-L13 -> 81
... A571: SO-10559 | B571: 46019 | C571: =MONTH(B571) -> 12 | D571: East | E571: Omar Farooq | F571: Laptop Air 13 | G571: =IFERROR(INDEX(Products!$B$2:$B$13,MATCH(F571,Products!$A$2:$A$13,0)),"Unknown") -> Laptops | H571: 3 | I571: =IFERROR(INDEX(Products!$C$2:$C$13,MATCH(F571,Products!$A$2:$A$13,0)),0) -> 780 | J571: =H571*I571 -> 2340 | K571: =IFERROR(INDEX(Products!$D$2:$D$13,MATCH(F571,Products!$A$2:$A$13,0)),0) -> 590 | L571: =H571*K571 -> 1770 | M571: =J571-L571 -> 570

Sheet Products
A1: Product | B1: Category | C1: Unit Price ($) | D1: Unit Cost ($) | E1: Margin %
A2: Laptop Pro 14 | B2: Laptops | C2: 950 | D2: 720 | E2: =IFERROR((C2-D2)/C2,0) -> 0.24210526
A3: Laptop Air 13 | B3: Laptops | C3: 780 | D3: 590 | E3: =IFERROR((C3-D3)/C3,0) -> 0.24358974
A4: Gaming Laptop X | B4: Laptops | C4: 1350 | D4: 1040 | E4: =IFERROR((C4-D4)/C4,0) -> 0.22962963
A5: Phone S23 | B5: Phones | C5: 640 | D5: 470 | E5: =IFERROR((C5-D5)/C5,0) -> 0.265625
A6: Phone Lite | B6: Phones | C6: 290 | D6: 205 | E6: =IFERROR((C6-D6)/C6,0) -> 0.29310345
A7: Tablet 11 | B7: Tablets | C7: 420 | D7: 300 | E7: =IFERROR((C7-D7)/C7,0) -> 0.28571429
A8: Tablet Mini | B8: Tablets | C8: 260 | D8: 180 | E8: =IFERROR((C8-D8)/C8,0) -> 0.30769231
A9: Wireless Earbuds | B9: Accessories | C9: 85 | D9: 38 | E9: =IFERROR((C9-D9)/C9,0) -> 0.55294118
A10: Smart Watch | B10: Accessories | C10: 190 | D10: 115 | E10: =IFERROR((C10-D10)/C10,0) -> 0.39473684
A11: USB-C Hub | B11: Accessories | C11: 45 | D11: 18 | E11: =IFERROR((C11-D11)/C11,0) -> 0.6
A12: 27in Monitor | B12: Monitors | C12: 310 | D12: 225 | E12: =IFERROR((C12-D12)/C12,0) -> 0.27419355
A13: Curved Monitor 32 | B13: Monitors | C13: 480 | D13: 350 | E13: =IFERROR((C13-D13)/C13,0) -> 0.27083333
A15: Blue numbers are inputs. Change a price or cost and the whole workbook updates.

Sheet Targets
A1: Month | B1: North Target ($) | C1: South Target ($) | D1: East Target ($) | E1: West Target ($) | F1: All Regions ($)
A2: Jan | B2: 8500 | C2: 10500 | D2: 11000 | E2: 12000 | F2: =SUM(B2:E2) -> 42000
A3: Feb | B3: 8000 | C3: 10000 | D3: 10500 | E3: 11500 | F3: =SUM(B3:E3) -> 40000
A4: Mar | B4: 9500 | C4: 12000 | D4: 12500 | E4: 13500 | F4: =SUM(B4:E4) -> 47500
A5: Apr | B5: 10000 | C5: 12500 | D5: 13000 | E5: 14500 | F5: =SUM(B5:E5) -> 50000
A6: May | B6: 10500 | C6: 13000 | D6: 14000 | E6: 15000 | F6: =SUM(B6:E6) -> 52500
A7: Jun | B7: 10500 | C7: 13000 | D7: 14000 | E7: 15000 | F7: =SUM(B7:E7) -> 52500
A8: Jul | B8: 10000 | C8: 12500 | D8: 13000 | E8: 14500 | F8: =SUM(B8:E8) -> 50000
A9: Aug | B9: 11000 | C9: 14000 | D9: 14500 | E9: 16000 | F9: =SUM(B9:E9) -> 55500
A10: Sep | B10: 11500 | C10: 14500 | D10: 15000 | E10: 16500 | F10: =SUM(B10:E10) -> 57500
A11: Oct | B11: 12000 | C11: 15000 | D11: 16000 | E11: 17500 | F11: =SUM(B11:E11) -> 60500
A12: Nov | B12: 14500 | C12: 18000 | D12: 18500 | E12: 20500 | F12: =SUM(B12:E12) -> 71500
A13: Dec | B13: 16000 | C13: 20000 | D13: 21000 | E13: 23000 | F13: =SUM(B13:E13) -> 80000
A15: Blue numbers are monthly sales targets (inputs).

Sheet Calc
A1: Helper sheet for the Top 5 products table. No need to edit.
A2: Product | B2: Revenue ($) | C2: Rank Key
A3: =Products!A2 -> Laptop Pro 14 | B3: =SUMPRODUCT(('Sales Data'!$F$2:$F$571=A3)*(((Dashboard!$C$5="All")+('Sales Data'!$D$2:$D$571=Dashboard!$C$5))>0)*'Sales Data'!$J$2:$J$571) -> 100700 | C3: =B3+ROW()/100000 -> 100700
A4: =Products!A3 -> Laptop Air 13 | B4: =SUMPRODUCT(('Sales Data'!$F$2:$F$571=A4)*(((Dashboard!$C$5="All")+('Sales Data'!$D$2:$D$571=Dashboard!$C$5))>0)*'Sales Data'!$J$2:$J$571) -> 94380 | C4: =B4+ROW()/100000 -> 94380
A5: =Products!A4 -> Gaming Laptop X | B5: =SUMPRODUCT(('Sales Data'!$F$2:$F$571=A5)*(((Dashboard!$C$5="All")+('Sales Data'!$D$2:$D$571=Dashboard!$C$5))>0)*'Sales Data'!$J$2:$J$571) -> 71550 | C5: =B5+ROW()/100000 -> 71550
A6: =Products!A5 -> Phone S23 | B6: =SUMPRODUCT(('Sales Data'!$F$2:$F$571=A6)*(((Dashboard!$C$5="All")+('Sales Data'!$D$2:$D$571=Dashboard!$C$5))>0)*'Sales Data'!$J$2:$J$571) -> 64640 | C6: =B6+ROW()/100000 -> 64640
A7: =Products!A6 -> Phone Lite | B7: =SUMPRODUCT(('Sales Data'!$F$2:$F$571=A7)*(((Dashboard!$C$5="All")+('Sales Data'!$D$2:$D$571=Dashboard!$C$5))>0)*'Sales Data'!$J$2:$J$571) -> 41760 | C7: =B7+ROW()/100000 -> 41760
A8: =Products!A7 -> Tablet 11 | B8: =SUMPRODUCT(('Sales Data'!$F$2:$F$571=A8)*(((Dashboard!$C$5="All")+('Sales Data'!$D$2:$D$571=Dashboard!$C$5))>0)*'Sales Data'!$J$2:$J$571) -> 33180 | C8: =B8+ROW()/100000 -> 33180
A9: =Products!A8 -> Tablet Mini | B9: =SUMPRODUCT(('Sales Data'!$F$2:$F$571=A9)*(((Dashboard!$C$5="All")+('Sales Data'!$D$2:$D$571=Dashboard!$C$5))>0)*'Sales Data'!$J$2:$J$571) -> 20540 | C9: =B9+ROW()/100000 -> 20540
A10: =Products!A9 -> Wireless Earbuds | B10: =SUMPRODUCT(('Sales Data'!$F$2:$F$571=A10)*(((Dashboard!$C$5="All")+('Sales Data'!$D$2:$D$571=Dashboard!$C$5))>0)*'Sales Data'!$J$2:$J$571) -> 61200 | C10: =B10+ROW()/100000 -> 61200
A11: =Products!A10 -> Smart Watch | B11: =SUMPRODUCT(('Sales Data'!$F$2:$F$571=A11)*(((Dashboard!$C$5="All")+('Sales Data'!$D$2:$D$571=Dashboard!$C$5))>0)*'Sales Data'!$J$2:$J$571) -> 77520 | C11: =B11+ROW()/100000 -> 77520
A12: =Products!A11 -> USB-C Hub | B12: =SUMPRODUCT(('Sales Data'!$F$2:$F$571=A12)*(((Dashboard!$C$5="All")+('Sales Data'!$D$2:$D$571=Dashboard!$C$5))>0)*'Sales Data'!$J$2:$J$571) -> 25380 | C12: =B12+ROW()/100000 -> 25380
A13: =Products!A12 -> 27in Monitor | B13: =SUMPRODUCT(('Sales Data'!$F$2:$F$571=A13)*(((Dashboard!$C$5="All")+('Sales Data'!$D$2:$D$571=Dashboard!$C$5))>0)*'Sales Data'!$J$2:$J$571) -> 15190 | C13: =B13+ROW()/100000 -> 15190
A14: =Products!A13 -> Curved Monitor 32 | B14: =SUMPRODUCT(('Sales Data'!$F$2:$F$571=A14)*(((Dashboard!$C$5="All")+('Sales Data'!$D$2:$D$571=Dashboard!$C$5))>0)*'Sales Data'!$J$2:$J$571) -> 25440 | C14: =B14+ROW()/100000 -> 25440
